odoo/addons/ssi_task_work_log/README.rst
odoo/addons/ssi_task_work_log/__init__.py
odoo/addons/ssi_task_work_log/__manifest__.py
odoo/addons/ssi_task_work_log/models/__init__.py
odoo/addons/ssi_task_work_log/models/project_task.py
odoo/addons/ssi_task_work_log/models/task_type.py
odoo/addons/ssi_task_work_log/static/description/icon.png
odoo/addons/ssi_task_work_log/views/project_task_views.xml
odoo/addons/ssi_task_work_log/views/task_type_views.xml
odoo/addons/ssi_task_work_log/wizards/__init__.py
odoo/addons/ssi_task_work_log/wizards/create_sucessor_task.py
odoo14_addon_ssi_task_work_log-14.0.1.8.0.dist-info/METADATA
odoo14_addon_ssi_task_work_log-14.0.1.8.0.dist-info/WHEEL
odoo14_addon_ssi_task_work_log-14.0.1.8.0.dist-info/top_level.txt
odoo14_addon_ssi_task_work_log-14.0.1.8.0.dist-info/RECORD
